TGGateway/__init__.py
TGGateway/_api.py
TGGateway/_api_async.py
TGGateway/exceptions.py
TGGateway/types.py
pytggateway-2.0.0.dist-info/LICENSE
pytggateway-2.0.0.dist-info/METADATA
pytggateway-2.0.0.dist-info/WHEEL
pytggateway-2.0.0.dist-info/top_level.txt
pytggateway-2.0.0.dist-info/RECORD
