Metadata-Version: 2.2
Name: PyTGGateway
Version: 2.0.0
Summary: Telegram Gateway API Wrapper
Home-page: https://github.com/Sasivarnasarma/TGGateway
Download-URL: https://github.com/Sasivarnasarma/TGGateway/archive/v2.0.0.zip
Author: Sasivarnasarma
Author-email: Sasivarnasarma <sasivarnasarma@protonmail.com>
License: MIT
Project-URL: Homepage, https://github.com/Sasivarnasarma/TGGateway
Project-URL: Repository, https://github.com/Sasivarnasarma/TGGateway
Project-URL: Download, https://github.com/Sasivarnasarma/TGGateway/archive/v1.0.3.zip
Classifier: License :: OSI Approved :: MIT License
Classifier: Operating System :: OS Independent
Classifier: Programming Language :: Python
Classifier: Programming Language :: Python :: 3
Classifier: Programming Language :: Python :: 3.7
Classifier: Programming Language :: Python :: 3.8
Classifier: Programming Language :: Python :: 3.9
Classifier: Programming Language :: Python :: 3.10
Classifier: Programming Language :: Python :: 3.11
Classifier: Programming Language :: Python :: 3.12
Requires-Python: >=3.7
License-File: LICENSE
Requires-Dist: httpx
Dynamic: author
Dynamic: download-url
Dynamic: home-page
Dynamic: requires-python
